LICENSE
MANIFEST.in
README.rst
setup.py
django_timesickle.egg-info/PKG-INFO
django_timesickle.egg-info/SOURCES.txt
django_timesickle.egg-info/dependency_links.txt
django_timesickle.egg-info/requires.txt
django_timesickle.egg-info/top_level.txt
timesickle/__init__.py
timesickle/datetime.py
timesickle/tests.py
timesickle/templates/timesickle-test-default-now.html
timesickle/templates/timesickle-test-default-today.html
timesickle/templatetags/__init__.py
timesickle/templatetags/timesickle.py