Metadata-Version: 1.1
Name: django-timesickle
Version: 0.2
Summary: Template name resolution for Django class-based views
Home-page: https://github.com/jleeothon/timesickle
Author: Johnny Lee
Author-email: jleeothon@outlook.com
License: MIT
Platform: UNKNOWN
Classifier: Environment :: Web Environment
Classifier: Framework :: Django
Classifier: Intended Audience :: Developers
Classifier: License :: OSI Approved :: MIT License
Classifier: Operating System :: OS Independent
Classifier: Programming Language :: Python
Classifier: Programming Language :: Python :: 3.4
Classifier: Topic :: Internet :: WWW/HTTP :: Dynamic Content
